miproxy/__init__.py
miproxy/__version__.py
miproxy/utils.py
miproxy-1.0.7.dist-info/METADATA
miproxy-1.0.7.dist-info/WHEEL
miproxy-1.0.7.dist-info/top_level.txt
miproxy-1.0.7.dist-info/RECORD
